cloudfeeds_client/__init__.py
rax_cloudfeeds-0.0.3.dist-info/METADATA
rax_cloudfeeds-0.0.3.dist-info/WHEEL
rax_cloudfeeds-0.0.3.dist-info/top_level.txt
rax_cloudfeeds-0.0.3.dist-info/RECORD
