Metadata-Version: 2.1
Name: rax-cloudfeeds
Version: 0.0.3
Summary: Client for Cloud Feeds
Home-page: https://github.rackspace.com/andrew-dorrycott/cloudfeeds_client.git
Author: Customer And Racker Experience Team
Author-email: CARE-CORERackers@rackspace.com
License: UNKNOWN
Platform: UNKNOWN
Classifier: Programming Language :: Python :: 3.6
Classifier: Operating System :: OS Independent
